trabalho_final/__init__.py
trabalho_final-0.1.0.dist-info/WHEEL
trabalho_final-0.1.0.dist-info/METADATA
trabalho_final-0.1.0.dist-info/RECORD
